dswell/__init__.py
dswell/cli.py
dswell/daemon.py
dswell/logger.py
dswell/pending.py
dswell/printer.py
dswell/utils.py
dswell/subcmds/__init__.py
dswell/subcmds/create.py
dswell/subcmds/list.py
dswell-0.1.0.dist-info/METADATA
dswell-0.1.0.dist-info/WHEEL
dswell-0.1.0.dist-info/entry_points.txt
dswell-0.1.0.dist-info/licenses/LICENSE
dswell-0.1.0.dist-info/RECORD
